<BackupInst xmlns="http://www.microsoft.com/GroupPolicy/GPOOperations/Manifest"><GPOGuid><![CDATA[{08B506AD-3F61-4284-AFA9-335A1D514F41}]]></GPOGuid><GPODomain><![CDATA[orgkit.org]]></GPODomain><GPODomainGuid><![CDATA[{8c5d0bed-d6a0-42b1-97a8-2da258d17f5c}]]></GPODomainGuid><GPODomainController><![CDATA[DC1OK.orgkit.org]]></GPODomainController><BackupTime><![CDATA[2019-05-25T07:12:31]]></BackupTime><ID><![CDATA[{203C9708-5A01-4B7F-B1C2-44AE82921905}]]></ID><Comment><![CDATA[]]></Comment><GPODisplayName><![CDATA[Security-AuditTripwires]]></GPODisplayName></BackupInst>
